rpa_lazada/__init__.py
rpa_lazada/api/BillApi.py
rpa_lazada/api/EarnestAmountApi.py
rpa_lazada/api/IncomeSummaryApi.py
rpa_lazada/api/PaymentBillApi.py
rpa_lazada/api/PromoApi.py
rpa_lazada/api/ReadyGrantApi.py
rpa_lazada/api/ShopApi.py
rpa_lazada/api/WalletBalanceApi.py
rpa_lazada/api/__init__.py
rpa_lazada/command/__init__.py
rpa_lazada/command/ads/__init__.py
rpa_lazada/command/ads/service/PromoService.py
rpa_lazada/command/ads/service/__init__.py
rpa_lazada/command/amount/__init__.py
rpa_lazada/command/amount/service/AmountService.py
rpa_lazada/command/amount/service/__init__.py
rpa_lazada/command/bill/__init__.py
rpa_lazada/command/bill/service/BillService.py
rpa_lazada/command/bill/service/__init__.py
rpa_lazada/service/LazadaService.py
rpa_lazada/service/__init__.py
rpa_lazada-1.0.8.dist-info/LICENSE
rpa_lazada-1.0.8.dist-info/METADATA
rpa_lazada-1.0.8.dist-info/WHEEL
rpa_lazada-1.0.8.dist-info/top_level.txt
rpa_lazada-1.0.8.dist-info/RECORD
